quant1x_xtquant-2025.5.26.dist-info/licenses/LICENSE
xtquant/__init__.py
xtquant/datacenter.cp310-win_amd64.pyd
xtquant/datacenter.cp311-win_amd64.pyd
xtquant/datacenter.cp312-win_amd64.pyd
xtquant/datacenter.cp313-win_amd64.pyd
xtquant/datacenter.cp36-win_amd64.pyd
xtquant/datacenter.cp37-win_amd64.pyd
xtquant/datacenter.cp38-win_amd64.pyd
xtquant/datacenter.cp39-win_amd64.pyd
xtquant/datacenter_shared.dll
xtquant/libeay32.dll
xtquant/log4cxx.dll
xtquant/msvcp140.dll
xtquant/ssleay32.dll
xtquant/vcruntime140.dll
xtquant/xtconn.py
xtquant/xtconstant.py
xtquant/xtdata.ini
xtquant/xtdata.log4cxx
xtquant/xtdata.py
xtquant/xtdata_config.py
xtquant/xtdatacenter.py
xtquant/xtextend.py
xtquant/xtpythonclient.cp310-win_amd64.pyd
xtquant/xtpythonclient.cp311-win_amd64.pyd
xtquant/xtpythonclient.cp312-win_amd64.pyd
xtquant/xtpythonclient.cp313-win_amd64.pyd
xtquant/xtpythonclient.cp36-win_amd64.pyd
xtquant/xtpythonclient.cp37-win_amd64.pyd
xtquant/xtpythonclient.cp38-win_amd64.pyd
xtquant/xtpythonclient.cp39-win_amd64.pyd
xtquant/xtstocktype.py
xtquant/xttools.py
xtquant/xttrader.py
xtquant/xttype.py
xtquant/xtutil.py
xtquant/xtview.py
xtquant/metatable/__init__.py
xtquant/metatable/get_arrow.py
xtquant/metatable/get_bson.py
xtquant/metatable/meta_config.py
xtquant/qmttools/__init__.py
xtquant/qmttools/contextinfo.py
xtquant/qmttools/functions.py
xtquant/qmttools/stgentry.py
xtquant/qmttools/stgframe.py
xtquant/xtbson/__init__.py
xtquant/xtbson/bson36/__init__.py
xtquant/xtbson/bson36/_cbson.cp36-win_amd64.pyd
xtquant/xtbson/bson36/_helpers.py
xtquant/xtbson/bson36/binary.py
xtquant/xtbson/bson36/code.py
xtquant/xtbson/bson36/codec_options.py
xtquant/xtbson/bson36/dbref.py
xtquant/xtbson/bson36/decimal128.py
xtquant/xtbson/bson36/errors.py
xtquant/xtbson/bson36/int64.py
xtquant/xtbson/bson36/json_util.py
xtquant/xtbson/bson36/max_key.py
xtquant/xtbson/bson36/min_key.py
xtquant/xtbson/bson36/objectid.py
xtquant/xtbson/bson36/raw_bson.py
xtquant/xtbson/bson36/regex.py
xtquant/xtbson/bson36/son.py
quant1x_xtquant-2025.5.26.dist-info/METADATA
quant1x_xtquant-2025.5.26.dist-info/WHEEL
quant1x_xtquant-2025.5.26.dist-info/top_level.txt
quant1x_xtquant-2025.5.26.dist-info/RECORD
