Metadata-Version: 2.4
Name: quant1x-xtquant
Version: 2025.5.26
Summary: Quant1X XtQuant
Home-page: https://gitee.com/quant1x/xtquant
Author: wangfeng
Author-email: wangfengxy@sina.cn
License: MIT license
Keywords: quant1x xtquant
Classifier: Development Status :: 2 - Pre-Alpha
Classifier: Intended Audience :: Developers
Classifier: License :: OSI Approved :: MIT License
Classifier: Natural Language :: English
Classifier: Programming Language :: Python :: 3
Classifier: Programming Language :: Python :: 3.8
Classifier: Programming Language :: Python :: 3.9
Classifier: Programming Language :: Python :: 3.10
Classifier: Programming Language :: Python :: 3.11
Classifier: Programming Language :: Python :: 3.12
License-File: LICENSE
Requires-Dist: setuptools~=78.0.0
Requires-Dist: twine~=6.1.0
Requires-Dist: wheel~=0.45.1
Requires-Dist: pymongo~=4.7.0
Requires-Dist: future~=1.0.0
Requires-Dist: numpy~=2.3.0
Requires-Dist: pandas~=2.3.0
Requires-Dist: PyYAML~=6.0.2
Requires-Dist: pywin32==311
Dynamic: author
Dynamic: author-email
Dynamic: classifier
Dynamic: description
Dynamic: home-page
Dynamic: keywords
Dynamic: license
Dynamic: license-file
Dynamic: requires-dist
Dynamic: summary
